[
  {
    "version": "latest",
    "url": "/DbContextBuilder/versions/latest/"
  },
  {
    "version": "v0.4.0",
    "url": "/DbContextBuilder/versions/v0.4.0/"
  },
  {
    "version": "v0.3.3",
    "url": "/DbContextBuilder/versions/v0.3.3/"
  },
  {
    "version": "v0.3.2-rc1",
    "url": "/DbContextBuilder/versions/v0.3.2-rc1/"
  },
  {
    "version": "v0.3.1-rc1",
    "url": "/DbContextBuilder/versions/v0.3.1-rc1/"
  },
  {
    "version": "v0.3.0-rc4",
    "url": "/DbContextBuilder/versions/v0.3.0-rc4/"
  },
  {
    "version": "v0.3.0-rc3",
    "url": "/DbContextBuilder/versions/v0.3.0-rc3/"
  },
  {
    "version": "v0.3.0-rc2",
    "url": "/DbContextBuilder/versions/v0.3.0-rc2/"
  },
  {
    "version": "v0.3.0-rc1",
    "url": "/DbContextBuilder/versions/v0.3.0-rc1/"
  },
  {
    "version": "v0.2.0",
    "url": "/DbContextBuilder/versions/v0.2.0/"
  },
  {
    "version": "v0.1.0-prerelease",
    "url": "/DbContextBuilder/versions/v0.1.0-prerelease/"
  },
  {
    "version": "v0.1.0-prelease7",
    "url": "/DbContextBuilder/versions/v0.1.0-prelease7/"
  },
  {
    "version": "v0.1.0-prelease6",
    "url": "/DbContextBuilder/versions/v0.1.0-prelease6/"
  },
  {
    "version": "v0.1.0-prelease5",
    "url": "/DbContextBuilder/versions/v0.1.0-prelease5/"
  },
  {
    "version": "v0.1.0-prelease4",
    "url": "/DbContextBuilder/versions/v0.1.0-prelease4/"
  },
  {
    "version": "v0.1.0-prelease3",
    "url": "/DbContextBuilder/versions/v0.1.0-prelease3/"
  },
  {
    "version": "v0.1.0-prelease2",
    "url": "/DbContextBuilder/versions/v0.1.0-prelease2/"
  },
  {
    "version": "v0.1.0-prelease",
    "url": "/DbContextBuilder/versions/v0.1.0-prelease/"
  }
]
