
{"items":[{"name":"Wolfgang.DbContextBuilderCore","href":"Wolfgang.DbContextBuilderCore.html","topicHref":"Wolfgang.DbContextBuilderCore.html","topicUid":"Wolfgang.DbContextBuilderCore","type":"Namespace","items":[{"name":"DbContextBuilderAutoFixtureExtensions","href":"Wolfgang.DbContextBuilderCore.DbContextBuilderAutoFixtureExtensions.html","topicHref":"Wolfgang.DbContextBuilderCore.DbContextBuilderAutoFixtureExtensions.html","topicUid":"Wolfgang.DbContextBuilderCore.DbContextBuilderAutoFixtureExtensions","type":"Class"},{"name":"DbContextBuilderSqliteExtensions","href":"Wolfgang.DbContextBuilderCore.DbContextBuilderSqliteExtensions.html","topicHref":"Wolfgang.DbContextBuilderCore.DbContextBuilderSqliteExtensions.html","topicUid":"Wolfgang.DbContextBuilderCore.DbContextBuilderSqliteExtensions","type":"Class"},{"name":"DbContextBuilder<T>","href":"Wolfgang.DbContextBuilderCore.DbContextBuilder-1.html","topicHref":"Wolfgang.DbContextBuilderCore.DbContextBuilder-1.html","topicUid":"Wolfgang.DbContextBuilderCore.DbContextBuilder`1","type":"Class"},{"name":"ICreateDbContext","href":"Wolfgang.DbContextBuilderCore.ICreateDbContext.html","topicHref":"Wolfgang.DbContextBuilderCore.ICreateDbContext.html","topicUid":"Wolfgang.DbContextBuilderCore.ICreateDbContext","type":"Interface"},{"name":"ICreateRandomEntities","href":"Wolfgang.DbContextBuilderCore.ICreateRandomEntities.html","topicHref":"Wolfgang.DbContextBuilderCore.ICreateRandomEntities.html","topicUid":"Wolfgang.DbContextBuilderCore.ICreateRandomEntities","type":"Interface"},{"name":"SqliteForMsSqlServerModelCustomizer","href":"Wolfgang.DbContextBuilderCore.SqliteForMsSqlServerModelCustomizer.html","topicHref":"Wolfgang.DbContextBuilderCore.SqliteForMsSqlServerModelCustomizer.html","topicUid":"Wolfgang.DbContextBuilderCore.SqliteForMsSqlServerModelCustomizer","type":"Class"},{"name":"SqliteModelCustomizer","href":"Wolfgang.DbContextBuilderCore.SqliteModelCustomizer.html","topicHref":"Wolfgang.DbContextBuilderCore.SqliteModelCustomizer.html","topicUid":"Wolfgang.DbContextBuilderCore.SqliteModelCustomizer","type":"Class"}]}],"memberLayout":"SamePage","pdf":true}
